[{"shipment_id": 205, "type": "\u9032\u5009", "category_name": "\u96fb\u6e90\u4f9b\u61c9\u5668", "product_sn": "230600400769", "customer_name": "\u4e09\u4ec1", "product_name": "REVOLUTION D.F. X (ERT1050EWT)", "note": "", "created_date": "2023-12-05 03:12:26"}, {"shipment_id": 205, "type": "\u9032\u5009", "category_name": "\u96fb\u6e90\u4f9b\u61c9\u5668", "product_sn": "230600400879", "customer_name": "\u4e09\u4ec1", "product_name": "REVOLUTION D.F. X (ERT1050EWT)", "note": "", "created_date": "2023-12-05 03:12:26"}, {"shipment_id": 205, "type": "\u9032\u5009", "category_name": "\u96fb\u6e90\u4f9b\u61c9\u5668", "product_sn": "230600400792", "customer_name": "\u4e09\u4ec1", "product_name": "REVOLUTION D.F. X (ERT1050EWT)", "note": "", "created_date": "2023-12-05 03:12:26"}, {"shipment_id": 205, "type": "\u9032\u5009", "category_name": "\u96fb\u6e90\u4f9b\u61c9\u5668", "product_sn": "230600400887", "customer_name": "\u4e09\u4ec1", "product_name": "REVOLUTION D.F. X (ERT1050EWT)", "note": "", "created_date": "2023-12-05 03:12:26"}, {"shipment_id": 204, "type": "\u9032\u5009", "category_name": "\u96fb\u6e90\u4f9b\u61c9\u5668", "product_sn": "230600400890", "customer_name": "\u4e09\u4ec1", "product_name": "REVOLUTION D.F. X (ERT1050EWT)", "note": "", "created_date": "2023-12-05 03:09:33"}, {"shipment_id": 204, "type": "\u9032\u5009", "category_name": "\u96fb\u6e90\u4f9b\u61c9\u5668", "product_sn": "230600400891", "customer_name": "\u4e09\u4ec1", "product_name": "REVOLUTION D.F. X (ERT1050EWT)", "note": "", "created_date": "2023-12-05 03:09:33"}, {"shipment_id": 204, "type": "\u9032\u5009", "category_name": "\u96fb\u6e90\u4f9b\u61c9\u5668", "product_sn": "230600400894", "customer_name": "\u4e09\u4ec1", "product_name": "REVOLUTION D.F. X (ERT1050EWT)", "note": "", "created_date": "2023-12-05 03:09:33"}, {"shipment_id": 204, "type": "\u9032\u5009", "category_name": "\u96fb\u6e90\u4f9b\u61c9\u5668", "product_sn": "230600400892", "customer_name": "\u4e09\u4ec1", "product_name": "REVOLUTION D.F. X (ERT1050EWT)", "note": "", "created_date": "2023-12-05 03:09:33"}, {"shipment_id": 204, "type": "\u9032\u5009", "category_name": "\u96fb\u6e90\u4f9b\u61c9\u5668", "product_sn": "230600400895", "customer_name": "\u4e09\u4ec1", "product_name": "REVOLUTION D.F. X (ERT1050EWT)", "note": "", "created_date": "2023-12-05 03:09:33"}, {"shipment_id": 204, "type": "\u9032\u5009", "category_name": "\u96fb\u6e90\u4f9b\u61c9\u5668", "product_sn": "230600400886", "customer_name": "\u4e09\u4ec1", "product_name": "REVOLUTION D.F. X (ERT1050EWT)", "note": "", "created_date": "2023-12-05 03:09:33"}]