[{"shipment_id": 162, "type": "\u51fa\u5009", "category_name": "\u5176\u4ed6\u5468\u908a", "product_sn": "999005", "customer_name": "\u65b9\u7f8e\u65b9", "product_name": "DIEGO", "note": "", "created_date": "2023-11-23 02:10:11"}, {"shipment_id": 152, "type": "\u51fa\u5009", "category_name": "\u5176\u4ed6\u5468\u908a", "product_sn": "999010", "customer_name": "\u65b9\u7f8e\u65b9", "product_name": "DIEGO", "note": null, "created_date": "2023-11-22 06:14:56"}, {"shipment_id": 152, "type": "\u51fa\u5009", "category_name": "\u5176\u4ed6\u5468\u908a", "product_sn": "999011", "customer_name": "\u65b9\u7f8e\u65b9", "product_name": "DIEGO", "note": null, "created_date": "2023-11-22 06:14:56"}, {"shipment_id": 152, "type": "\u51fa\u5009", "category_name": "\u5176\u4ed6\u5468\u908a", "product_sn": "999012", "customer_name": "\u65b9\u7f8e\u65b9", "product_name": "DIEGO", "note": null, "created_date": "2023-11-22 06:14:56"}, {"shipment_id": 152, "type": "\u51fa\u5009", "category_name": "\u5176\u4ed6\u5468\u908a", "product_sn": "999013", "customer_name": "\u65b9\u7f8e\u65b9", "product_name": "DIEGO", "note": null, "created_date": "2023-11-22 06:14:56"}, {"shipment_id": 152, "type": "\u51fa\u5009", "category_name": "\u5176\u4ed6\u5468\u908a", "product_sn": "999014", "customer_name": "\u65b9\u7f8e\u65b9", "product_name": "DIEGO", "note": null, "created_date": "2023-11-22 06:14:56"}, {"shipment_id": 152, "type": "\u51fa\u5009", "category_name": "\u5176\u4ed6\u5468\u908a", "product_sn": "999015", "customer_name": "\u65b9\u7f8e\u65b9", "product_name": "DIEGO", "note": null, "created_date": "2023-11-22 06:14:56"}, {"shipment_id": 152, "type": "\u51fa\u5009", "category_name": "\u5176\u4ed6\u5468\u908a", "product_sn": "999016", "customer_name": "\u65b9\u7f8e\u65b9", "product_name": "DIEGO", "note": null, "created_date": "2023-11-22 06:14:56"}, {"shipment_id": 152, "type": "\u51fa\u5009", "category_name": "\u5176\u4ed6\u5468\u908a", "product_sn": "999017", "customer_name": "\u65b9\u7f8e\u65b9", "product_name": "DIEGO", "note": null, "created_date": "2023-11-22 06:14:56"}, {"shipment_id": 152, "type": "\u51fa\u5009", "category_name": "\u5176\u4ed6\u5468\u908a", "product_sn": "999018", "customer_name": "\u65b9\u7f8e\u65b9", "product_name": "DIEGO", "note": null, "created_date": "2023-11-22 06:14:56"}, {"shipment_id": 152, "type": "\u51fa\u5009", "category_name": "\u5176\u4ed6\u5468\u908a", "product_sn": "999019", "customer_name": "\u65b9\u7f8e\u65b9", "product_name": "DIEGO", "note": null, "created_date": "2023-11-22 06:14:56"}, {"shipment_id": 152, "type": "\u51fa\u5009", "category_name": "\u5176\u4ed6\u5468\u908a", "product_sn": "999020", "customer_name": "\u65b9\u7f8e\u65b9", "product_name": "DIEGO", "note": null, "created_date": "2023-11-22 06:14:56"}, {"shipment_id": 152, "type": "\u51fa\u5009", "category_name": "\u5176\u4ed6\u5468\u908a", "product_sn": "999021", "customer_name": "\u65b9\u7f8e\u65b9", "product_name": "DIEGO", "note": null, "created_date": "2023-11-22 06:14:56"}, {"shipment_id": 152, "type": "\u51fa\u5009", "category_name": "\u5176\u4ed6\u5468\u908a", "product_sn": "999022", "customer_name": "\u65b9\u7f8e\u65b9", "product_name": "DIEGO", "note": null, "created_date": "2023-11-22 06:14:56"}, {"shipment_id": 152, "type": "\u51fa\u5009", "category_name": "\u5176\u4ed6\u5468\u908a", "product_sn": "999023", "customer_name": "\u65b9\u7f8e\u65b9", "product_name": "DIEGO", "note": null, "created_date": "2023-11-22 06:14:56"}, {"shipment_id": 152, "type": "\u51fa\u5009", "category_name": "\u5176\u4ed6\u5468\u908a", "product_sn": "999024", "customer_name": "\u65b9\u7f8e\u65b9", "product_name": "DIEGO", "note": null, "created_date": "2023-11-22 06:14:56"}, {"shipment_id": 152, "type": "\u51fa\u5009", "category_name": "\u5176\u4ed6\u5468\u908a", "product_sn": "999025", "customer_name": "\u65b9\u7f8e\u65b9", "product_name": "DIEGO", "note": null, "created_date": "2023-11-22 06:14:56"}, {"shipment_id": 152, "type": "\u51fa\u5009", "category_name": "\u5176\u4ed6\u5468\u908a", "product_sn": "999026", "customer_name": "\u65b9\u7f8e\u65b9", "product_name": "DIEGO", "note": null, "created_date": "2023-11-22 06:14:56"}, {"shipment_id": 152, "type": "\u51fa\u5009", "category_name": "\u5176\u4ed6\u5468\u908a", "product_sn": "999027", "customer_name": "\u65b9\u7f8e\u65b9", "product_name": "DIEGO", "note": null, "created_date": "2023-11-22 06:14:56"}, {"shipment_id": 152, "type": "\u51fa\u5009", "category_name": "\u5176\u4ed6\u5468\u908a", "product_sn": "999028", "customer_name": "\u65b9\u7f8e\u65b9", "product_name": "DIEGO", "note": null, "created_date": "2023-11-22 06:14:56"}, {"shipment_id": 152, "type": "\u51fa\u5009", "category_name": "\u5176\u4ed6\u5468\u908a", "product_sn": "999029", "customer_name": "\u65b9\u7f8e\u65b9", "product_name": "DIEGO", "note": null, "created_date": "2023-11-22 06:14:56"}, {"shipment_id": 152, "type": "\u51fa\u5009", "category_name": "\u5176\u4ed6\u5468\u908a", "product_sn": "999030", "customer_name": "\u65b9\u7f8e\u65b9", "product_name": "DIEGO", "note": null, "created_date": "2023-11-22 06:14:56"}, {"shipment_id": 152, "type": "\u51fa\u5009", "category_name": "\u5176\u4ed6\u5468\u908a", "product_sn": "999031", "customer_name": "\u65b9\u7f8e\u65b9", "product_name": "DIEGO", "note": null, "created_date": "2023-11-22 06:14:56"}, {"shipment_id": 152, "type": "\u51fa\u5009", "category_name": "\u5176\u4ed6\u5468\u908a", "product_sn": "999032", "customer_name": "\u65b9\u7f8e\u65b9", "product_name": "DIEGO", "note": null, "created_date": "2023-11-22 06:14:56"}, {"shipment_id": 152, "type": "\u51fa\u5009", "category_name": "\u5176\u4ed6\u5468\u908a", "product_sn": "999033", "customer_name": "\u65b9\u7f8e\u65b9", "product_name": "DIEGO", "note": null, "created_date": "2023-11-22 06:14:56"}, {"shipment_id": 152, "type": "\u51fa\u5009", "category_name": "\u5176\u4ed6\u5468\u908a", "product_sn": "999034", "customer_name": "\u65b9\u7f8e\u65b9", "product_name": "DIEGO", "note": null, "created_date": "2023-11-22 06:14:56"}, {"shipment_id": 152, "type": "\u51fa\u5009", "category_name": "\u5176\u4ed6\u5468\u908a", "product_sn": "999035", "customer_name": "\u65b9\u7f8e\u65b9", "product_name": "DIEGO", "note": null, "created_date": "2023-11-22 06:14:56"}, {"shipment_id": 152, "type": "\u51fa\u5009", "category_name": "\u5176\u4ed6\u5468\u908a", "product_sn": "999036", "customer_name": "\u65b9\u7f8e\u65b9", "product_name": "DIEGO", "note": null, "created_date": "2023-11-22 06:14:56"}, {"shipment_id": 152, "type": "\u51fa\u5009", "category_name": "\u5176\u4ed6\u5468\u908a", "product_sn": "999037", "customer_name": "\u65b9\u7f8e\u65b9", "product_name": "DIEGO", "note": null, "created_date": "2023-11-22 06:14:56"}, {"shipment_id": 152, "type": "\u51fa\u5009", "category_name": "\u5176\u4ed6\u5468\u908a", "product_sn": "999038", "customer_name": "\u65b9\u7f8e\u65b9", "product_name": "DIEGO", "note": null, "created_date": "2023-11-22 06:14:56"}, {"shipment_id": 152, "type": "\u51fa\u5009", "category_name": "\u5176\u4ed6\u5468\u908a", "product_sn": "999039", "customer_name": "\u65b9\u7f8e\u65b9", "product_name": "DIEGO", "note": null, "created_date": "2023-11-22 06:14:56"}, {"shipment_id": 152, "type": "\u51fa\u5009", "category_name": "\u5176\u4ed6\u5468\u908a", "product_sn": "999040", "customer_name": "\u65b9\u7f8e\u65b9", "product_name": "DIEGO", "note": null, "created_date": "2023-11-22 06:14:56"}, {"shipment_id": 152, "type": "\u51fa\u5009", "category_name": "\u5176\u4ed6\u5468\u908a", "product_sn": "999041", "customer_name": "\u65b9\u7f8e\u65b9", "product_name": "DIEGO", "note": null, "created_date": "2023-11-22 06:14:56"}, {"shipment_id": 152, "type": "\u51fa\u5009", "category_name": "\u5176\u4ed6\u5468\u908a", "product_sn": "999042", "customer_name": "\u65b9\u7f8e\u65b9", "product_name": "DIEGO", "note": null, "created_date": "2023-11-22 06:14:56"}, {"shipment_id": 152, "type": "\u51fa\u5009", "category_name": "\u5176\u4ed6\u5468\u908a", "product_sn": "999043", "customer_name": "\u65b9\u7f8e\u65b9", "product_name": "DIEGO", "note": null, "created_date": "2023-11-22 06:14:56"}, {"shipment_id": 152, "type": "\u51fa\u5009", "category_name": "\u5176\u4ed6\u5468\u908a", "product_sn": "999044", "customer_name": "\u65b9\u7f8e\u65b9", "product_name": "DIEGO", "note": null, "created_date": "2023-11-22 06:14:56"}, {"shipment_id": 152, "type": "\u51fa\u5009", "category_name": "\u5176\u4ed6\u5468\u908a", "product_sn": "999045", "customer_name": "\u65b9\u7f8e\u65b9", "product_name": "DIEGO", "note": null, "created_date": "2023-11-22 06:14:56"}, {"shipment_id": 152, "type": "\u51fa\u5009", "category_name": "\u5176\u4ed6\u5468\u908a", "product_sn": "999046", "customer_name": "\u65b9\u7f8e\u65b9", "product_name": "DIEGO", "note": null, "created_date": "2023-11-22 06:14:56"}, {"shipment_id": 152, "type": "\u51fa\u5009", "category_name": "\u5176\u4ed6\u5468\u908a", "product_sn": "999047", "customer_name": "\u65b9\u7f8e\u65b9", "product_name": "DIEGO", "note": null, "created_date": "2023-11-22 06:14:56"}, {"shipment_id": 152, "type": "\u51fa\u5009", "category_name": "\u5176\u4ed6\u5468\u908a", "product_sn": "999048", "customer_name": "\u65b9\u7f8e\u65b9", "product_name": "DIEGO", "note": null, "created_date": "2023-11-22 06:14:56"}, {"shipment_id": 152, "type": "\u51fa\u5009", "category_name": "\u5176\u4ed6\u5468\u908a", "product_sn": "999049", "customer_name": "\u65b9\u7f8e\u65b9", "product_name": "DIEGO", "note": null, "created_date": "2023-11-22 06:14:56"}, {"shipment_id": 152, "type": "\u51fa\u5009", "category_name": "\u5176\u4ed6\u5468\u908a", "product_sn": "999050", "customer_name": "\u65b9\u7f8e\u65b9", "product_name": "DIEGO", "note": null, "created_date": "2023-11-22 06:14:56"}, {"shipment_id": 151, "type": "\u51fa\u5009", "category_name": "\u5176\u4ed6\u5468\u908a", "product_sn": "999010", "customer_name": "MOMO", "product_name": "DIEGO", "note": null, "created_date": "2023-11-22 06:11:23"}, {"shipment_id": 151, "type": "\u51fa\u5009", "category_name": "\u5176\u4ed6\u5468\u908a", "product_sn": "999011", "customer_name": "MOMO", "product_name": "DIEGO", "note": null, "created_date": "2023-11-22 06:11:23"}, {"shipment_id": 151, "type": "\u51fa\u5009", "category_name": "\u5176\u4ed6\u5468\u908a", "product_sn": "999012", "customer_name": "MOMO", "product_name": "DIEGO", "note": null, "created_date": "2023-11-22 06:11:23"}, {"shipment_id": 151, "type": "\u51fa\u5009", "category_name": "\u5176\u4ed6\u5468\u908a", "product_sn": "999013", "customer_name": "MOMO", "product_name": "DIEGO", "note": null, "created_date": "2023-11-22 06:11:23"}, {"shipment_id": 151, "type": "\u51fa\u5009", "category_name": "\u5176\u4ed6\u5468\u908a", "product_sn": "999014", "customer_name": "MOMO", "product_name": "DIEGO", "note": null, "created_date": "2023-11-22 06:11:23"}, {"shipment_id": 151, "type": "\u51fa\u5009", "category_name": "\u5176\u4ed6\u5468\u908a", "product_sn": "999015", "customer_name": "MOMO", "product_name": "DIEGO", "note": null, "created_date": "2023-11-22 06:11:23"}, {"shipment_id": 151, "type": "\u51fa\u5009", "category_name": "\u5176\u4ed6\u5468\u908a", "product_sn": "999016", "customer_name": "MOMO", "product_name": "DIEGO", "note": null, "created_date": "2023-11-22 06:11:23"}, {"shipment_id": 151, "type": "\u51fa\u5009", "category_name": "\u5176\u4ed6\u5468\u908a", "product_sn": "999017", "customer_name": "MOMO", "product_name": "DIEGO", "note": null, "created_date": "2023-11-22 06:11:23"}, {"shipment_id": 151, "type": "\u51fa\u5009", "category_name": "\u5176\u4ed6\u5468\u908a", "product_sn": "999018", "customer_name": "MOMO", "product_name": "DIEGO", "note": null, "created_date": "2023-11-22 06:11:23"}, {"shipment_id": 151, "type": "\u51fa\u5009", "category_name": "\u5176\u4ed6\u5468\u908a", "product_sn": "999019", "customer_name": "MOMO", "product_name": "DIEGO", "note": null, "created_date": "2023-11-22 06:11:23"}, {"shipment_id": 151, "type": "\u51fa\u5009", "category_name": "\u5176\u4ed6\u5468\u908a", "product_sn": "999020", "customer_name": "MOMO", "product_name": "DIEGO", "note": null, "created_date": "2023-11-22 06:11:23"}, {"shipment_id": 151, "type": "\u51fa\u5009", "category_name": "\u5176\u4ed6\u5468\u908a", "product_sn": "999021", "customer_name": "MOMO", "product_name": "DIEGO", "note": null, "created_date": "2023-11-22 06:11:23"}, {"shipment_id": 151, "type": "\u51fa\u5009", "category_name": "\u5176\u4ed6\u5468\u908a", "product_sn": "999022", "customer_name": "MOMO", "product_name": "DIEGO", "note": null, "created_date": "2023-11-22 06:11:23"}, {"shipment_id": 151, "type": "\u51fa\u5009", "category_name": "\u5176\u4ed6\u5468\u908a", "product_sn": "999023", "customer_name": "MOMO", "product_name": "DIEGO", "note": null, "created_date": "2023-11-22 06:11:23"}, {"shipment_id": 151, "type": "\u51fa\u5009", "category_name": "\u5176\u4ed6\u5468\u908a", "product_sn": "999024", "customer_name": "MOMO", "product_name": "DIEGO", "note": null, "created_date": "2023-11-22 06:11:23"}, {"shipment_id": 151, "type": "\u51fa\u5009", "category_name": "\u5176\u4ed6\u5468\u908a", "product_sn": "999025", "customer_name": "MOMO", "product_name": "DIEGO", "note": null, "created_date": "2023-11-22 06:11:23"}, {"shipment_id": 151, "type": "\u51fa\u5009", "category_name": "\u5176\u4ed6\u5468\u908a", "product_sn": "999026", "customer_name": "MOMO", "product_name": "DIEGO", "note": null, "created_date": "2023-11-22 06:11:23"}, {"shipment_id": 151, "type": "\u51fa\u5009", "category_name": "\u5176\u4ed6\u5468\u908a", "product_sn": "999027", "customer_name": "MOMO", "product_name": "DIEGO", "note": null, "created_date": "2023-11-22 06:11:23"}, {"shipment_id": 151, "type": "\u51fa\u5009", "category_name": "\u5176\u4ed6\u5468\u908a", "product_sn": "999028", "customer_name": "MOMO", "product_name": "DIEGO", "note": null, "created_date": "2023-11-22 06:11:23"}, {"shipment_id": 151, "type": "\u51fa\u5009", "category_name": "\u5176\u4ed6\u5468\u908a", "product_sn": "999029", "customer_name": "MOMO", "product_name": "DIEGO", "note": null, "created_date": "2023-11-22 06:11:23"}, {"shipment_id": 151, "type": "\u51fa\u5009", "category_name": "\u5176\u4ed6\u5468\u908a", "product_sn": "999030", "customer_name": "MOMO", "product_name": "DIEGO", "note": null, "created_date": "2023-11-22 06:11:23"}, {"shipment_id": 151, "type": "\u51fa\u5009", "category_name": "\u5176\u4ed6\u5468\u908a", "product_sn": "999031", "customer_name": "MOMO", "product_name": "DIEGO", "note": null, "created_date": "2023-11-22 06:11:23"}, {"shipment_id": 151, "type": "\u51fa\u5009", "category_name": "\u5176\u4ed6\u5468\u908a", "product_sn": "999032", "customer_name": "MOMO", "product_name": "DIEGO", "note": null, "created_date": "2023-11-22 06:11:23"}, {"shipment_id": 151, "type": "\u51fa\u5009", "category_name": "\u5176\u4ed6\u5468\u908a", "product_sn": "999033", "customer_name": "MOMO", "product_name": "DIEGO", "note": null, "created_date": "2023-11-22 06:11:23"}, {"shipment_id": 151, "type": "\u51fa\u5009", "category_name": "\u5176\u4ed6\u5468\u908a", "product_sn": "999034", "customer_name": "MOMO", "product_name": "DIEGO", "note": null, "created_date": "2023-11-22 06:11:23"}, {"shipment_id": 151, "type": "\u51fa\u5009", "category_name": "\u5176\u4ed6\u5468\u908a", "product_sn": "999035", "customer_name": "MOMO", "product_name": "DIEGO", "note": null, "created_date": "2023-11-22 06:11:23"}, {"shipment_id": 151, "type": "\u51fa\u5009", "category_name": "\u5176\u4ed6\u5468\u908a", "product_sn": "999036", "customer_name": "MOMO", "product_name": "DIEGO", "note": null, "created_date": "2023-11-22 06:11:23"}, {"shipment_id": 151, "type": "\u51fa\u5009", "category_name": "\u5176\u4ed6\u5468\u908a", "product_sn": "999037", "customer_name": "MOMO", "product_name": "DIEGO", "note": null, "created_date": "2023-11-22 06:11:23"}, {"shipment_id": 151, "type": "\u51fa\u5009", "category_name": "\u5176\u4ed6\u5468\u908a", "product_sn": "999038", "customer_name": "MOMO", "product_name": "DIEGO", "note": null, "created_date": "2023-11-22 06:11:23"}, {"shipment_id": 151, "type": "\u51fa\u5009", "category_name": "\u5176\u4ed6\u5468\u908a", "product_sn": "999039", "customer_name": "MOMO", "product_name": "DIEGO", "note": null, "created_date": "2023-11-22 06:11:23"}, {"shipment_id": 151, "type": "\u51fa\u5009", "category_name": "\u5176\u4ed6\u5468\u908a", "product_sn": "999040", "customer_name": "MOMO", "product_name": "DIEGO", "note": null, "created_date": "2023-11-22 06:11:23"}, {"shipment_id": 135, "type": "\u51fa\u5009", "category_name": "\u96fb\u6e90\u4f9b\u61c9\u5668", "product_sn": "230600400558", "customer_name": "\u65b9\u7f8e\u65b9", "product_name": "REVOLUTION D.F. X (ERT850EWT)", "note": "", "created_date": "2023-11-21 02:31:57"}, {"shipment_id": 134, "type": "\u51fa\u5009", "category_name": "\u96fb\u6e90\u4f9b\u61c9\u5668", "product_sn": "230600400557", "customer_name": "\u65b9\u7f8e\u65b9", "product_name": "REVOLUTION D.F. X (ERT850EWT)", "note": "", "created_date": "2023-11-21 02:31:51"}, {"shipment_id": 133, "type": "\u51fa\u5009", "category_name": "\u96fb\u6e90\u4f9b\u61c9\u5668", "product_sn": "230600400556", "customer_name": "\u65b9\u7f8e\u65b9", "product_name": "REVOLUTION D.F. X (ERT850EWT)", "note": "", "created_date": "2023-11-21 02:31:44"}, {"shipment_id": 128, "type": "\u51fa\u5009", "category_name": "\u96fb\u6e90\u4f9b\u61c9\u5668", "product_sn": "230600400680", "customer_name": "\u78a9\u65b9\u79d1\u6280", "product_name": "REVOLUTION D.F. X (ERT850EWT)", "note": "", "created_date": "2023-11-21 02:22:41"}, {"shipment_id": 127, "type": "\u51fa\u5009", "category_name": "\u96fb\u6e90\u4f9b\u61c9\u5668", "product_sn": "230600400679", "customer_name": "\u78a9\u65b9\u79d1\u6280", "product_name": "REVOLUTION D.F. X (ERT850EWT)", "note": "", "created_date": "2023-11-21 02:22:30"}, {"shipment_id": 126, "type": "\u51fa\u5009", "category_name": "\u96fb\u6e90\u4f9b\u61c9\u5668", "product_sn": "230600400678", "customer_name": "\u78a9\u65b9\u79d1\u6280", "product_name": "REVOLUTION D.F. X (ERT850EWT)", "note": "", "created_date": "2023-11-21 02:22:22"}, {"shipment_id": 125, "type": "\u51fa\u5009", "category_name": "\u96fb\u6e90\u4f9b\u61c9\u5668", "product_sn": "230600400677", "customer_name": "\u78a9\u65b9\u79d1\u6280", "product_name": "REVOLUTION D.F. X (ERT850EWT)", "note": "", "created_date": "2023-11-21 02:22:14"}, {"shipment_id": 124, "type": "\u51fa\u5009", "category_name": "\u96fb\u6e90\u4f9b\u61c9\u5668", "product_sn": "230600400676", "customer_name": "\u78a9\u65b9\u79d1\u6280", "product_name": "REVOLUTION D.F. X (ERT850EWT)", "note": "", "created_date": "2023-11-21 02:22:03"}, {"shipment_id": 123, "type": "\u51fa\u5009", "category_name": "\u96fb\u6e90\u4f9b\u61c9\u5668", "product_sn": "230600400715", "customer_name": "\u78a9\u65b9\u79d1\u6280", "product_name": "REVOLUTION D.F. X (ERT850EWT)", "note": "", "created_date": "2023-11-21 02:21:46"}, {"shipment_id": 122, "type": "\u51fa\u5009", "category_name": "\u96fb\u6e90\u4f9b\u61c9\u5668", "product_sn": "230600400714", "customer_name": "\u78a9\u65b9\u79d1\u6280", "product_name": "REVOLUTION D.F. X (ERT850EWT)", "note": "", "created_date": "2023-11-21 02:21:39"}, {"shipment_id": 121, "type": "\u51fa\u5009", "category_name": "\u96fb\u6e90\u4f9b\u61c9\u5668", "product_sn": "230600400713", "customer_name": "\u78a9\u65b9\u79d1\u6280", "product_name": "REVOLUTION D.F. X (ERT850EWT)", "note": "", "created_date": "2023-11-21 02:21:31"}, {"shipment_id": 120, "type": "\u51fa\u5009", "category_name": "\u96fb\u6e90\u4f9b\u61c9\u5668", "product_sn": "230600400712", "customer_name": "\u78a9\u65b9\u79d1\u6280", "product_name": "REVOLUTION D.F. X (ERT850EWT)", "note": "", "created_date": "2023-11-21 02:21:22"}, {"shipment_id": 119, "type": "\u51fa\u5009", "category_name": "\u96fb\u6e90\u4f9b\u61c9\u5668", "product_sn": "230600400711", "customer_name": "\u78a9\u65b9\u79d1\u6280", "product_name": "REVOLUTION D.F. X (ERT850EWT)", "note": "", "created_date": "2023-11-21 02:21:04"}, {"shipment_id": 116, "type": "\u51fa\u5009", "category_name": "\u96fb\u6e90\u4f9b\u61c9\u5668", "product_sn": "230700402327", "customer_name": "\u65b9\u7f8e\u65b9", "product_name": "REVOLUTION D.F. X (ERT1200EWT)", "note": "", "created_date": "2023-11-21 02:18:46"}, {"shipment_id": 115, "type": "\u51fa\u5009", "category_name": "\u96fb\u6e90\u4f9b\u61c9\u5668", "product_sn": "230700402260", "customer_name": "\u65b9\u7f8e\u65b9", "product_name": "REVOLUTION D.F. X (ERT1200EWT)", "note": "", "created_date": "2023-11-21 02:18:32"}, {"shipment_id": 114, "type": "\u51fa\u5009", "category_name": "\u96fb\u6e90\u4f9b\u61c9\u5668", "product_sn": "230700402345", "customer_name": "\u65b9\u7f8e\u65b9", "product_name": "REVOLUTION D.F. X (ERT1200EWT)", "note": "", "created_date": "2023-11-21 02:18:15"}, {"shipment_id": 113, "type": "\u51fa\u5009", "category_name": "\u96fb\u6e90\u4f9b\u61c9\u5668", "product_sn": "230700402344", "customer_name": "\u65b9\u7f8e\u65b9", "product_name": "REVOLUTION D.F. X (ERT1200EWT)", "note": "", "created_date": "2023-11-21 02:18:08"}, {"shipment_id": 112, "type": "\u51fa\u5009", "category_name": "\u96fb\u6e90\u4f9b\u61c9\u5668", "product_sn": "230700402343", "customer_name": "\u65b9\u7f8e\u65b9", "product_name": "REVOLUTION D.F. X (ERT1200EWT)", "note": "", "created_date": "2023-11-21 02:18:02"}, {"shipment_id": 111, "type": "\u51fa\u5009", "category_name": "\u96fb\u6e90\u4f9b\u61c9\u5668", "product_sn": "230700402342", "customer_name": "\u65b9\u7f8e\u65b9", "product_name": "REVOLUTION D.F. X (ERT1200EWT)", "note": "", "created_date": "2023-11-21 02:17:55"}, {"shipment_id": 110, "type": "\u51fa\u5009", "category_name": "\u96fb\u6e90\u4f9b\u61c9\u5668", "product_sn": "230700402341", "customer_name": "\u65b9\u7f8e\u65b9", "product_name": "REVOLUTION D.F. X (ERT1200EWT)", "note": "", "created_date": "2023-11-21 02:17:49"}, {"shipment_id": 109, "type": "\u51fa\u5009", "category_name": "\u96fb\u6e90\u4f9b\u61c9\u5668", "product_sn": "230700402295", "customer_name": "\u65b9\u7f8e\u65b9", "product_name": "REVOLUTION D.F. X (ERT1200EWT)", "note": "", "created_date": "2023-11-21 02:17:27"}, {"shipment_id": 108, "type": "\u51fa\u5009", "category_name": "\u96fb\u6e90\u4f9b\u61c9\u5668", "product_sn": "230700402294", "customer_name": "\u65b9\u7f8e\u65b9", "product_name": "REVOLUTION D.F. X (ERT1200EWT)", "note": "", "created_date": "2023-11-21 02:17:19"}, {"shipment_id": 107, "type": "\u51fa\u5009", "category_name": "\u96fb\u6e90\u4f9b\u61c9\u5668", "product_sn": "230700402293", "customer_name": "\u65b9\u7f8e\u65b9", "product_name": "REVOLUTION D.F. X (ERT1200EWT)", "note": "", "created_date": "2023-11-21 02:17:12"}, {"shipment_id": 106, "type": "\u51fa\u5009", "category_name": "\u96fb\u6e90\u4f9b\u61c9\u5668", "product_sn": "230700402292", "customer_name": "\u65b9\u7f8e\u65b9", "product_name": "REVOLUTION D.F. X (ERT1200EWT)", "note": "", "created_date": "2023-11-21 02:17:06"}, {"shipment_id": 105, "type": "\u51fa\u5009", "category_name": "\u96fb\u6e90\u4f9b\u61c9\u5668", "product_sn": "230700402291", "customer_name": "\u65b9\u7f8e\u65b9", "product_name": "REVOLUTION D.F. X (ERT1200EWT)", "note": "", "created_date": "2023-11-21 02:16:58"}, {"shipment_id": 104, "type": "\u51fa\u5009", "category_name": "\u96fb\u6e90\u4f9b\u61c9\u5668", "product_sn": "230700400685", "customer_name": "\u65b9\u7f8e\u65b9", "product_name": "REVOLUTION D.F. X (ERT1200EWT)", "note": "", "created_date": "2023-11-21 02:16:32"}, {"shipment_id": 103, "type": "\u51fa\u5009", "category_name": "\u96fb\u6e90\u4f9b\u61c9\u5668", "product_sn": "230700400684", "customer_name": "\u65b9\u7f8e\u65b9", "product_name": "REVOLUTION D.F. X (ERT1200EWT)", "note": "", "created_date": "2023-11-21 02:16:23"}, {"shipment_id": 102, "type": "\u51fa\u5009", "category_name": "\u96fb\u6e90\u4f9b\u61c9\u5668", "product_sn": "230700400683", "customer_name": "\u65b9\u7f8e\u65b9", "product_name": "REVOLUTION D.F. X (ERT1200EWT)", "note": "", "created_date": "2023-11-21 02:16:17"}, {"shipment_id": 101, "type": "\u51fa\u5009", "category_name": "\u96fb\u6e90\u4f9b\u61c9\u5668", "product_sn": "230700400682", "customer_name": "\u65b9\u7f8e\u65b9", "product_name": "REVOLUTION D.F. X (ERT1200EWT)", "note": "", "created_date": "2023-11-21 02:16:09"}, {"shipment_id": 100, "type": "\u51fa\u5009", "category_name": "\u96fb\u6e90\u4f9b\u61c9\u5668", "product_sn": "230700400681", "customer_name": "\u65b9\u7f8e\u65b9", "product_name": "REVOLUTION D.F. X (ERT1200EWT)", "note": "", "created_date": "2023-11-21 02:16:01"}, {"shipment_id": 99, "type": "\u51fa\u5009", "category_name": "\u96fb\u6e90\u4f9b\u61c9\u5668", "product_sn": "230700400990", "customer_name": "\u65b9\u7f8e\u65b9", "product_name": "REVOLUTION D.F. X (ERT1200EWT)", "note": "", "created_date": "2023-11-21 02:13:52"}, {"shipment_id": 98, "type": "\u51fa\u5009", "category_name": "\u96fb\u6e90\u4f9b\u61c9\u5668", "product_sn": "230700400989", "customer_name": "\u65b9\u7f8e\u65b9", "product_name": "REVOLUTION D.F. X (ERT1200EWT)", "note": "", "created_date": "2023-11-21 02:13:44"}, {"shipment_id": 97, "type": "\u51fa\u5009", "category_name": "\u96fb\u6e90\u4f9b\u61c9\u5668", "product_sn": "230700400988", "customer_name": "\u65b9\u7f8e\u65b9", "product_name": "REVOLUTION D.F. X (ERT1200EWT)", "note": "", "created_date": "2023-11-21 02:13:38"}, {"shipment_id": 96, "type": "\u51fa\u5009", "category_name": "\u96fb\u6e90\u4f9b\u61c9\u5668", "product_sn": "230700400987", "customer_name": "\u65b9\u7f8e\u65b9", "product_name": "REVOLUTION D.F. X (ERT1200EWT)", "note": "", "created_date": "2023-11-21 02:13:31"}, {"shipment_id": 95, "type": "\u51fa\u5009", "category_name": "\u96fb\u6e90\u4f9b\u61c9\u5668", "product_sn": "230700400986", "customer_name": "\u65b9\u7f8e\u65b9", "product_name": "REVOLUTION D.F. X (ERT1200EWT)", "note": "", "created_date": "2023-11-21 02:13:23"}, {"shipment_id": 94, "type": "\u51fa\u5009", "category_name": "\u96fb\u6e90\u4f9b\u61c9\u5668", "product_sn": "230600400763", "customer_name": "\u65b9\u7f8e\u65b9", "product_name": "REVOLUTION D.F. X (ERT1050EWT)", "note": "", "created_date": "2023-11-21 02:12:48"}, {"shipment_id": 93, "type": "\u51fa\u5009", "category_name": "\u96fb\u6e90\u4f9b\u61c9\u5668", "product_sn": "230600400855", "customer_name": "\u65b9\u7f8e\u65b9", "product_name": "REVOLUTION D.F. X (ERT1050EWT)", "note": "", "created_date": "2023-11-21 02:12:36"}, {"shipment_id": 92, "type": "\u51fa\u5009", "category_name": "\u96fb\u6e90\u4f9b\u61c9\u5668", "product_sn": "230600400860", "customer_name": "\u65b9\u7f8e\u65b9", "product_name": "REVOLUTION D.F. X (ERT1050EWT)", "note": "", "created_date": "2023-11-21 02:12:18"}, {"shipment_id": 91, "type": "\u51fa\u5009", "category_name": "\u96fb\u6e90\u4f9b\u61c9\u5668", "product_sn": "230600400859", "customer_name": "\u65b9\u7f8e\u65b9", "product_name": "REVOLUTION D.F. X (ERT1050EWT)", "note": "", "created_date": "2023-11-21 02:12:10"}, {"shipment_id": 90, "type": "\u51fa\u5009", "category_name": "\u96fb\u6e90\u4f9b\u61c9\u5668", "product_sn": "230600400858", "customer_name": "\u65b9\u7f8e\u65b9", "product_name": "REVOLUTION D.F. X (ERT1050EWT)", "note": "", "created_date": "2023-11-21 02:12:02"}, {"shipment_id": 89, "type": "\u51fa\u5009", "category_name": "\u96fb\u6e90\u4f9b\u61c9\u5668", "product_sn": "230600400857", "customer_name": "\u65b9\u7f8e\u65b9", "product_name": "REVOLUTION D.F. X (ERT1050EWT)", "note": "", "created_date": "2023-11-21 02:11:54"}, {"shipment_id": 88, "type": "\u51fa\u5009", "category_name": "\u96fb\u6e90\u4f9b\u61c9\u5668", "product_sn": "230600400856", "customer_name": "\u65b9\u7f8e\u65b9", "product_name": "REVOLUTION D.F. X (ERT1050EWT)", "note": "", "created_date": "2023-11-21 02:11:45"}, {"shipment_id": 87, "type": "\u51fa\u5009", "category_name": "\u96fb\u6e90\u4f9b\u61c9\u5668", "product_sn": "230600400870", "customer_name": "\u65b9\u7f8e\u65b9", "product_name": "REVOLUTION D.F. X (ERT1050EWT)", "note": "", "created_date": "2023-11-21 02:11:21"}, {"shipment_id": 86, "type": "\u51fa\u5009", "category_name": "\u96fb\u6e90\u4f9b\u61c9\u5668", "product_sn": "230600400869", "customer_name": "\u65b9\u7f8e\u65b9", "product_name": "REVOLUTION D.F. X (ERT1050EWT)", "note": "", "created_date": "2023-11-21 02:11:09"}, {"shipment_id": 85, "type": "\u51fa\u5009", "category_name": "\u96fb\u6e90\u4f9b\u61c9\u5668", "product_sn": "230600400868", "customer_name": "\u65b9\u7f8e\u65b9", "product_name": "REVOLUTION D.F. X (ERT1050EWT)", "note": "", "created_date": "2023-11-21 02:11:01"}, {"shipment_id": 84, "type": "\u51fa\u5009", "category_name": "\u96fb\u6e90\u4f9b\u61c9\u5668", "product_sn": "230600400867", "customer_name": "\u65b9\u7f8e\u65b9", "product_name": "REVOLUTION D.F. X (ERT1050EWT)", "note": "", "created_date": "2023-11-21 02:10:53"}, {"shipment_id": 83, "type": "\u51fa\u5009", "category_name": "\u96fb\u6e90\u4f9b\u61c9\u5668", "product_sn": "230600400866", "customer_name": "\u65b9\u7f8e\u65b9", "product_name": "REVOLUTION D.F. X (ERT1050EWT)", "note": "", "created_date": "2023-11-21 02:10:44"}, {"shipment_id": 82, "type": "\u51fa\u5009", "category_name": "\u96fb\u6e90\u4f9b\u61c9\u5668", "product_sn": "230600400898", "customer_name": "\u65b9\u7f8e\u65b9", "product_name": "REVOLUTION D.F. X (ERT1050EWT)", "note": "", "created_date": "2023-11-21 02:10:17"}, {"shipment_id": 81, "type": "\u51fa\u5009", "category_name": "\u96fb\u6e90\u4f9b\u61c9\u5668", "product_sn": "230600400900", "customer_name": "\u65b9\u7f8e\u65b9", "product_name": "REVOLUTION D.F. X (ERT1050EWT)", "note": "", "created_date": "2023-11-21 02:09:55"}, {"shipment_id": 80, "type": "\u51fa\u5009", "category_name": "\u96fb\u6e90\u4f9b\u61c9\u5668", "product_sn": "230600400899", "customer_name": "\u65b9\u7f8e\u65b9", "product_name": "REVOLUTION D.F. X (ERT1050EWT)", "note": "", "created_date": "2023-11-21 02:09:45"}, {"shipment_id": 79, "type": "\u51fa\u5009", "category_name": "\u96fb\u6e90\u4f9b\u61c9\u5668", "product_sn": "230600400897", "customer_name": "\u65b9\u7f8e\u65b9", "product_name": "REVOLUTION D.F. X (ERT1050EWT)", "note": "", "created_date": "2023-11-21 02:09:23"}, {"shipment_id": 78, "type": "\u51fa\u5009", "category_name": "\u96fb\u6e90\u4f9b\u61c9\u5668", "product_sn": "230600400896", "customer_name": "\u65b9\u7f8e\u65b9", "product_name": "REVOLUTION D.F. X (ERT1050EWT)", "note": "", "created_date": "2023-11-21 02:09:14"}, {"shipment_id": 77, "type": "\u51fa\u5009", "category_name": "\u96fb\u6e90\u4f9b\u61c9\u5668", "product_sn": "230600400865", "customer_name": "\u65b9\u7f8e\u65b9", "product_name": "REVOLUTION D.F. X (ERT1050EWT)", "note": "", "created_date": "2023-11-21 02:08:54"}, {"shipment_id": 76, "type": "\u51fa\u5009", "category_name": "\u96fb\u6e90\u4f9b\u61c9\u5668", "product_sn": "230600400864", "customer_name": "\u65b9\u7f8e\u65b9", "product_name": "REVOLUTION D.F. X (ERT1050EWT)", "note": "", "created_date": "2023-11-21 02:08:46"}, {"shipment_id": 75, "type": "\u51fa\u5009", "category_name": "\u96fb\u6e90\u4f9b\u61c9\u5668", "product_sn": "230600400863", "customer_name": "\u65b9\u7f8e\u65b9", "product_name": "REVOLUTION D.F. X (ERT1050EWT)", "note": "", "created_date": "2023-11-21 02:08:39"}, {"shipment_id": 74, "type": "\u51fa\u5009", "category_name": "\u96fb\u6e90\u4f9b\u61c9\u5668", "product_sn": "230600400862", "customer_name": "\u65b9\u7f8e\u65b9", "product_name": "REVOLUTION D.F. X (ERT1050EWT)", "note": "", "created_date": "2023-11-21 02:08:30"}, {"shipment_id": 73, "type": "\u51fa\u5009", "category_name": "\u96fb\u6e90\u4f9b\u61c9\u5668", "product_sn": "230600400861", "customer_name": "\u65b9\u7f8e\u65b9", "product_name": "REVOLUTION D.F. X (ERT1050EWT)", "note": "", "created_date": "2023-11-21 02:08:22"}, {"shipment_id": 72, "type": "\u51fa\u5009", "category_name": "\u96fb\u6e90\u4f9b\u61c9\u5668", "product_sn": "230600400555", "customer_name": "\u65b9\u7f8e\u65b9", "product_name": "REVOLUTION D.F. X (ERT850EWT)", "note": "", "created_date": "2023-11-21 02:08:00"}, {"shipment_id": 71, "type": "\u51fa\u5009", "category_name": "\u96fb\u6e90\u4f9b\u61c9\u5668", "product_sn": "230600400554", "customer_name": "\u65b9\u7f8e\u65b9", "product_name": "REVOLUTION D.F. X (ERT850EWT)", "note": "", "created_date": "2023-11-21 02:07:52"}, {"shipment_id": 70, "type": "\u51fa\u5009", "category_name": "\u96fb\u6e90\u4f9b\u61c9\u5668", "product_sn": "230600400553", "customer_name": "\u65b9\u7f8e\u65b9", "product_name": "REVOLUTION D.F. X (ERT850EWT)", "note": "", "created_date": "2023-11-21 02:07:44"}, {"shipment_id": 69, "type": "\u51fa\u5009", "category_name": "\u96fb\u6e90\u4f9b\u61c9\u5668", "product_sn": "230600400552", "customer_name": "\u65b9\u7f8e\u65b9", "product_name": "REVOLUTION D.F. X (ERT850EWT)", "note": "", "created_date": "2023-11-21 02:07:36"}, {"shipment_id": 68, "type": "\u51fa\u5009", "category_name": "\u96fb\u6e90\u4f9b\u61c9\u5668", "product_sn": "230600400551", "customer_name": "\u65b9\u7f8e\u65b9", "product_name": "REVOLUTION D.F. X (ERT850EWT)", "note": "", "created_date": "2023-11-21 02:07:28"}, {"shipment_id": 67, "type": "\u51fa\u5009", "category_name": "\u96fb\u6e90\u4f9b\u61c9\u5668", "product_sn": "230600400580", "customer_name": "\u65b9\u7f8e\u65b9", "product_name": "REVOLUTION D.F. X (ERT850EWT)", "note": "", "created_date": "2023-11-21 02:06:49"}, {"shipment_id": 66, "type": "\u51fa\u5009", "category_name": "\u96fb\u6e90\u4f9b\u61c9\u5668", "product_sn": "230600400579", "customer_name": "\u65b9\u7f8e\u65b9", "product_name": "REVOLUTION D.F. X (ERT850EWT)", "note": "", "created_date": "2023-11-21 02:06:42"}, {"shipment_id": 65, "type": "\u51fa\u5009", "category_name": "\u96fb\u6e90\u4f9b\u61c9\u5668", "product_sn": "230600400578", "customer_name": "\u65b9\u7f8e\u65b9", "product_name": "REVOLUTION D.F. X (ERT850EWT)", "note": "", "created_date": "2023-11-21 02:06:34"}, {"shipment_id": 64, "type": "\u51fa\u5009", "category_name": "\u96fb\u6e90\u4f9b\u61c9\u5668", "product_sn": "230600400577", "customer_name": "\u65b9\u7f8e\u65b9", "product_name": "REVOLUTION D.F. X (ERT850EWT)", "note": "", "created_date": "2023-11-21 02:06:27"}, {"shipment_id": 63, "type": "\u51fa\u5009", "category_name": "\u96fb\u6e90\u4f9b\u61c9\u5668", "product_sn": "230600400576", "customer_name": "\u65b9\u7f8e\u65b9", "product_name": "REVOLUTION D.F. X (ERT850EWT)", "note": "", "created_date": "2023-11-21 02:06:19"}, {"shipment_id": 62, "type": "\u51fa\u5009", "category_name": "\u96fb\u6e90\u4f9b\u61c9\u5668", "product_sn": "230600400675", "customer_name": "\u65b9\u7f8e\u65b9", "product_name": "REVOLUTION D.F. X (ERT850EWT)", "note": "", "created_date": "2023-11-21 02:04:04"}, {"shipment_id": 61, "type": "\u51fa\u5009", "category_name": "\u96fb\u6e90\u4f9b\u61c9\u5668", "product_sn": "230600400674", "customer_name": "\u65b9\u7f8e\u65b9", "product_name": "REVOLUTION D.F. X (ERT850EWT)", "note": "", "created_date": "2023-11-21 02:03:53"}, {"shipment_id": 60, "type": "\u51fa\u5009", "category_name": "\u96fb\u6e90\u4f9b\u61c9\u5668", "product_sn": "230600400673", "customer_name": "\u65b9\u7f8e\u65b9", "product_name": "REVOLUTION D.F. X (ERT850EWT)", "note": "", "created_date": "2023-11-21 02:03:40"}, {"shipment_id": 59, "type": "\u51fa\u5009", "category_name": "\u96fb\u6e90\u4f9b\u61c9\u5668", "product_sn": "230600400672", "customer_name": "\u65b9\u7f8e\u65b9", "product_name": "REVOLUTION D.F. X (ERT850EWT)", "note": "", "created_date": "2023-11-21 02:03:31"}, {"shipment_id": 58, "type": "\u51fa\u5009", "category_name": "\u96fb\u6e90\u4f9b\u61c9\u5668", "product_sn": "230600400671", "customer_name": "\u65b9\u7f8e\u65b9", "product_name": "REVOLUTION D.F. X (ERT850EWT)", "note": "", "created_date": "2023-11-21 02:03:21"}, {"shipment_id": 57, "type": "\u51fa\u5009", "category_name": "\u96fb\u6e90\u4f9b\u61c9\u5668", "product_sn": "230600400570", "customer_name": "\u65b9\u7f8e\u65b9", "product_name": "REVOLUTION D.F. X (ERT850EWT)", "note": "", "created_date": "2023-11-21 02:01:32"}, {"shipment_id": 56, "type": "\u51fa\u5009", "category_name": "\u96fb\u6e90\u4f9b\u61c9\u5668", "product_sn": "230600400569", "customer_name": "\u65b9\u7f8e\u65b9", "product_name": "REVOLUTION D.F. X (ERT850EWT)", "note": "\u539f\u672c\u70ba\u4e09\u4ec1", "created_date": "2023-11-21 02:01:20"}, {"shipment_id": 55, "type": "\u51fa\u5009", "category_name": "\u96fb\u6e90\u4f9b\u61c9\u5668", "product_sn": "230600400568", "customer_name": "\u65b9\u7f8e\u65b9", "product_name": "REVOLUTION D.F. X (ERT850EWT)", "note": "", "created_date": "2023-11-21 02:01:11"}, {"shipment_id": 53, "type": "\u51fa\u5009", "category_name": "\u96fb\u6e90\u4f9b\u61c9\u5668", "product_sn": "230600400567", "customer_name": "\u65b9\u7f8e\u65b9", "product_name": "REVOLUTION D.F. X (ERT850EWT)", "note": "", "created_date": "2023-11-21 02:00:27"}, {"shipment_id": 52, "type": "\u51fa\u5009", "category_name": "\u96fb\u6e90\u4f9b\u61c9\u5668", "product_sn": "230600400566", "customer_name": "\u4e09\u4ec1", "product_name": "REVOLUTION D.F. X (ERT850EWT)", "note": "", "created_date": "2023-11-21 02:00:16"}]